pyenvtools/__init__.py
pyenvtools/__main__.py
pyenvtools-0.1.0.dist-info/METADATA
pyenvtools-0.1.0.dist-info/WHEEL
pyenvtools-0.1.0.dist-info/RECORD
